cursor_rules_cli/__init__.py
cursor_rules_cli/downloader.py
cursor_rules_cli/installer.py
cursor_rules_cli/main.py
cursor_rules_cli/matcher.py
cursor_rules_cli/scanner.py
cursor_rules_cli/utils.py
cursor_rules-0.5.1.dist-info/LICENSE
cursor_rules-0.5.1.dist-info/METADATA
cursor_rules-0.5.1.dist-info/WHEEL
cursor_rules-0.5.1.dist-info/entry_points.txt
cursor_rules-0.5.1.dist-info/top_level.txt
cursor_rules-0.5.1.dist-info/RECORD
