Metadata-Version: 2.2
Name: cursor-rules
Version: 0.5.1
Summary: A CLI tool to scan projects and install relevant Cursor rules
Home-page: https://github.com/sanjeed5/awesome-cursor-rules-mdc
Author: sanjeed5
Author-email: hi@sanjeed.in
Keywords: cursor,rules,mdc,cli
Classifier: Development Status :: 3 - Alpha
Classifier: Intended Audience :: Developers
Classifier: License :: OSI Approved :: MIT License
Classifier: Programming Language :: Python :: 3
Classifier: Programming Language :: Python :: 3.8
Classifier: Programming Language :: Python :: 3.9
Classifier: Programming Language :: Python :: 3.10
Classifier: Programming Language :: Python :: 3.11
Requires-Python: >=3.8
License-File: LICENSE
Requires-Dist: requests>=2.25.0
Requires-Dist: colorama>=0.4.4
Requires-Dist: tqdm>=4.62.0
Requires-Dist: urllib3>=2.0.0
Requires-Dist: validators>=0.20.0
Dynamic: author
Dynamic: author-email
Dynamic: classifier
Dynamic: description
Dynamic: description-content-type
Dynamic: home-page
Dynamic: keywords
Dynamic: requires-dist
Dynamic: requires-python
Dynamic: summary
